kzapp/__init__.py
kzapp/__main__.py
kzapp-1.0.6.dist-info/METADATA
kzapp-1.0.6.dist-info/WHEEL
kzapp-1.0.6.dist-info/top_level.txt
kzapp-1.0.6.dist-info/RECORD
