Metadata-Version: 2.1
Name: kzapp
Version: 1.0.6
Summary: system resourse infomation viewer, for myself use, updating continuous
Home-page: UNKNOWN
Author: XieTian
Author-email: xietianaaa@qq.com
License: UNKNOWN
Platform: UNKNOWN
Requires-Python: >=3.6
Requires-Dist: psutil (>=5.9.8)
